Lightweight_AI/LWBNA_models.py
Lightweight_AI/Train_LWBNA.py
Lightweight_AI/__init__.py
Lightweight_AI-0.1.4.dist-info/LICENSE.md
Lightweight_AI-0.1.4.dist-info/METADATA
Lightweight_AI-0.1.4.dist-info/WHEEL
Lightweight_AI-0.1.4.dist-info/top_level.txt
Lightweight_AI-0.1.4.dist-info/RECORD
