Metadata-Version: 2.1
Name: Lightweight-AI
Version: 0.1.4
Summary: Lightweight deep learning model for biological image analysis.
Home-page: https://github.com/parmanandsharma/Lightweight_AI
Author: Parmanand Sharma
Author-email: sharmap.imr@gmail.com
License: UNKNOWN
Project-URL: Bug Reports, https://github.com/parmanandsharma/Lightweight_AI/issues
Project-URL: Source, https://github.com/parmanandsharma/Lightweight_AI
Platform: UNKNOWN
Classifier: Intended Audience :: Developers
Classifier: Intended Audience :: Science/Research
Classifier: Topic :: Scientific/Engineering :: Artificial Intelligence
Classifier: Topic :: Scientific/Engineering :: Image Recognition
Classifier: License :: OSI Approved :: MIT License
Classifier: Programming Language :: Python :: 3
Classifier: Programming Language :: Python :: 3.8
Classifier: Programming Language :: Python :: 3.9
Classifier: Programming Language :: Python :: 3.10
Requires-Python: >=3.8
Requires-Dist: numpy
Requires-Dist: opencv-python
Requires-Dist: pandas
